zenith/__init__.py
zenith/_core.cp310-win_amd64.pyd
zenith/engine.py
zenith/loader.py
zenith/scheduler.py
zenith/tensorflow/__init__.py
zenith/tensorflow/dataset.py
zenith/torch/__init__.py
zenith/torch/dataloader.py
zenith/torch/dataset.py
zenith_ai-0.3.4.dist-info/METADATA
zenith_ai-0.3.4.dist-info/WHEEL
zenith_ai-0.3.4.dist-info/RECORD
