Metadata-Version: 2.4
Name: zenith-ai
Version: 0.3.4
Classifier: Development Status :: 4 - Beta
Classifier: Intended Audience :: Developers
Classifier: Intended Audience :: Science/Research
Classifier: License :: OSI Approved :: Apache Software License
Classifier: Operating System :: POSIX :: Linux
Classifier: Operating System :: MacOS
Classifier: Programming Language :: Python :: 3
Classifier: Programming Language :: Python :: 3.10
Classifier: Programming Language :: Python :: 3.11
Classifier: Programming Language :: Python :: 3.12
Classifier: Programming Language :: Rust
Classifier: Topic :: Scientific/Engineering :: Artificial Intelligence
Classifier: Topic :: Software Development :: Libraries :: Python Modules
Requires-Dist: pyarrow>=14.0.0
Requires-Dist: numpy>=1.24.0
Requires-Dist: torch>=2.0.0 ; extra == 'torch'
Requires-Dist: tensorflow>=2.14.0 ; extra == 'tensorflow'
Requires-Dist: torch>=2.0.0 ; extra == 'all'
Requires-Dist: tensorflow>=2.14.0 ; extra == 'all'
Requires-Dist: pytest>=7.0.0 ; extra == 'dev'
Requires-Dist: pytest-benchmark>=4.0.0 ; extra == 'dev'
Requires-Dist: maturin>=1.4.0 ; extra == 'dev'
Provides-Extra: torch
Provides-Extra: tensorflow
Provides-Extra: all
Provides-Extra: dev
Summary: High-Performance Data Infrastructure for Machine Learning - Native Rust Performance
Keywords: machine-learning,deep-learning,pytorch,tensorflow,data-loading,high-performance,rust,gpu,training,ai
Author-email: Wahyu Ardiansyah <wahyu@zenith.dev>
License: Apache-2.0
Requires-Python: >=3.10
Project-URL: Homepage, https://github.com/vibeswithkk/Zenith-dataplane
Project-URL: Documentation, https://github.com/vibeswithkk/Zenith-dataplane#documentation
Project-URL: Repository, https://github.com/vibeswithkk/Zenith-dataplane
Project-URL: Issues, https://github.com/vibeswithkk/Zenith-dataplane/issues
